fastbencode/__init__.py
fastbencode/_bencode_py.py
fastbencode/_bencode_rs.cp314-win32.pyd
fastbencode/py.typed
fastbencode-0.3.9.dist-info/licenses/COPYING
fastbencode-0.3.9.dist-info/METADATA
fastbencode-0.3.9.dist-info/WHEEL
fastbencode-0.3.9.dist-info/top_level.txt
fastbencode-0.3.9.dist-info/RECORD
