Metadata-Version: 2.4
Name: fastbencode
Version: 0.3.9
Summary: Implementation of bencode with optional fast Rust extensions
Maintainer-email: Breezy Developers <breezy-core@googlegroups.com>
License-Expression: Apache-2.0
Project-URL: Homepage, https://github.com/breezy-team/fastbencode
Project-URL: GitHub, https://github.com/breezy-team/fastbencode
Classifier: Programming Language :: Python :: 3.10
Classifier: Programming Language :: Python :: 3.11
Classifier: Programming Language :: Python :: 3.12
Classifier: Programming Language :: Python :: 3.13
Classifier: Programming Language :: Python :: 3.14
Classifier: Programming Language :: Python :: Implementation :: CPython
Classifier: Programming Language :: Python :: Implementation :: PyPy
Classifier: Operating System :: POSIX
Classifier: Operating System :: Microsoft :: Windows
Requires-Python: >=3.10
License-File: COPYING
Provides-Extra: rust
Requires-Dist: setuptools-rust>=1.0.0; extra == "rust"
Provides-Extra: dev
Requires-Dist: ruff==0.14.6; extra == "dev"
Dynamic: license-file
